beanclerk/__init__.py
beanclerk/bean_helpers.py
beanclerk/clerk.py
beanclerk/cli.py
beanclerk/config.py
beanclerk/exceptions.py
beanclerk/importers/__init__.py
beanclerk/importers/banka_creditas.py
beanclerk/importers/fio_banka.py
beanclerk-0.0.13.dist-info/LICENSE
beanclerk-0.0.13.dist-info/METADATA
beanclerk-0.0.13.dist-info/WHEEL
beanclerk-0.0.13.dist-info/entry_points.txt
beanclerk-0.0.13.dist-info/top_level.txt
beanclerk-0.0.13.dist-info/RECORD
