Metadata-Version: 2.1
Name: beanclerk
Version: 0.0.13
Summary: Automation for Beancount
Author-email: Petr Beranek <petrberanek.mail@gmail.com>
License: GNU GENERAL PUBLIC LICENSE
Keywords: accounting,finance,beancount,automation,API
Classifier: Development Status :: 4 - Beta
Classifier: Environment :: Console
Classifier: Intended Audience :: End Users/Desktop
Classifier: Intended Audience :: Information Technology
Classifier: License :: OSI Approved :: GNU General Public License v2 (GPLv2)
Classifier: Operating System :: POSIX :: Linux
Classifier: Programming Language :: Python :: 3.11
Classifier: Topic :: Office/Business :: Financial :: Accounting
Requires-Python: >=3.11
License-File: LICENSE
Requires-Dist: PyYAML~=6.0
Requires-Dist: beancount~=3.0
Requires-Dist: click~=8.1
Requires-Dist: creditas==1.0.0.*
Requires-Dist: fio-banka~=3.0
Requires-Dist: lxml~=5.1
Requires-Dist: pydantic-settings~=2.0
Requires-Dist: pydantic~=2.0
Requires-Dist: rich~=13.4
